{
    "resourceType": "ValueSet",
    "id": "ValueSet-nNGM-SystemischeTherapie-Kategorie",
    "url": "http://uk-koeln.de/fhir/ValueSet/nNGM/SystemischeTherapieKategorie",
    "version": "1.0.0",
    "title": "ValueSet - nNGM - Systemische Therapie - Kategorie",
    "name": "ValueSet_nNGM_SystemischeTherapie_Kategorie",
    "status": "active",
    "compose": {
        "include": [
            {
                "system": "http://ncicb.nci.nih.gov/xml/owl/EVS/Thesaurus.owl",
                "concept": [
                    {
                        "code": "C25446",
                        "display": "Change"
                    },
                    {
                        "code": "C85582",
                        "display": "Current Therapy"
                    }
                ]
            },
            {
                "system": "http://terminology.hl7.org/CodeSystem/data-absent-reason",
                "concept": [
                    {
                        "code": "not-applicable",
                        "display": "Not Applicable"
                    }
                ]
            }
        ]
    },
    "expansion": {
        "identifier": "50a7dc69-cfcb-4a52-b513-fb119e70a85e",
        "timestamp": "2020-11-12T10:42:13+00:00",
        "total": 3,
        "contains": [
            {
                "system": "http://terminology.hl7.org/CodeSystem/data-absent-reason",
                "version": "4.0.1",
                "code": "not-applicable",
                "display": "Not Applicable"
            },
            {
                "system": "http://ncicb.nci.nih.gov/xml/owl/EVS/Thesaurus.owl",
                "code": "C25446",
                "display": "Change"
            },
            {
                "system": "http://ncicb.nci.nih.gov/xml/owl/EVS/Thesaurus.owl",
                "code": "C85582",
                "display": "Current Therapy"
            }
        ]
    }
}
